gradio_bbox_annotator/__init__.py
gradio_bbox_annotator/bbox_annotator.py
gradio_bbox_annotator/bbox_annotator.pyi
gradio_bbox_annotator/templates/component/index.js
gradio_bbox_annotator/templates/component/style.css
gradio_bbox_annotator/templates/example/index.js
gradio_bbox_annotator/templates/example/style.css
gradio_bbox_annotator-0.1.1.dist-info/METADATA
gradio_bbox_annotator-0.1.1.dist-info/WHEEL
gradio_bbox_annotator-0.1.1.dist-info/licenses/LICENSE
gradio_bbox_annotator-0.1.1.dist-info/RECORD
