Metadata-Version: 2.3
Name: gradio_bbox_annotator
Version: 0.1.1
Summary: Bounding box annotation tool that supports insertion and editing
Project-URL: repository, https://github.com/kyamagu/gradio-bbox-annotator
Project-URL: space, https://huggingface.co/spaces/kyamagu/gradio_bbox_annotator
Author-email: Kota Yamaguchi <yamaguchi_kota@cyberagent.co.jp>
License: Apache-2.0
Keywords: annotation,bbox,gradio-custom-component,image
Classifier: Development Status :: 3 - Alpha
Classifier: Operating System :: OS Independent
Classifier: Programming Language :: Python :: 3
Classifier: Programming Language :: Python :: 3 :: Only
Classifier: Programming Language :: Python :: 3.10
Classifier: Programming Language :: Python :: 3.11
Classifier: Programming Language :: Python :: 3.12
Classifier: Programming Language :: Python :: 3.13
Classifier: Topic :: Scientific/Engineering
Classifier: Topic :: Scientific/Engineering :: Artificial Intelligence
Classifier: Topic :: Scientific/Engineering :: Visualization
Requires-Python: >=3.10
Requires-Dist: gradio<6.0,>=4.0
Provides-Extra: dev
Requires-Dist: build; extra == 'dev'
Requires-Dist: twine; extra == 'dev'
